{
  "argentina": "/flags/argentina.svg",
  "australia": "/flags/australia.svg",
  "austria": "/flags/austria.svg",
  "canada": "/flags/canada.svg",
  "colombia": "/flags/colombia.svg",
  "estonia": "/flags/estonia.svg",
  "finland": "/flags/finland.svg",
  "france": "/flags/france.svg",
  "germany": "/flags/germany.svg",
  "india": "/flags/india.svg",
  "indonesia": "/flags/indonesia.svg",
  "malaysia": "/flags/malaysia.svg",
  "mexico": "/flags/mexico.svg",
  "singapore": "/flags/singapore.svg",
  "sweden": "/flags/sweden.svg",
  "switzerland": "/flags/switzerland.svg",
  "uae": "/flags/uae.svg",
  "uk": "/flags/uk.svg",
  "usa": "/flags/usa.svg",
  "vietnam": "/flags/vietnam.svg"
}
